myrecursion/recursion.py
MyRecursion-0.0.4.dist-info/METADATA
MyRecursion-0.0.4.dist-info/WHEEL
MyRecursion-0.0.4.dist-info/top_level.txt
MyRecursion-0.0.4.dist-info/RECORD
